src/__init__.py
src/analizador_monedas.py
tests/__init__.py
tests/test_integración_analizador.py
tests/test_unitario_analizador.py
UNAV_KRK-0.2.dist-info/LICENSE
UNAV_KRK-0.2.dist-info/METADATA
UNAV_KRK-0.2.dist-info/WHEEL
UNAV_KRK-0.2.dist-info/top_level.txt
UNAV_KRK-0.2.dist-info/RECORD
