Metadata-Version: 2.1
Name: UNAV_KRK
Version: 0.2
Summary: Descarga y plotea monedas de kraken
Home-page: https://github.com/TapiaR/AnaliMon/tree/master
Author: A.Tapia
Author-email: altapia7@gmail.com
Requires-Python: >=3.6
License-File: LICENSE
Requires-Dist: krakenex
Requires-Dist: pandas
Requires-Dist: matplotlib
Requires-Dist: mplfinance
